MANIFEST.in
README.md
setup.cfg
setup.py
dupandas/Indexer.py
dupandas/__init__.py
dupandas.egg-info/PKG-INFO
dupandas.egg-info/SOURCES.txt
dupandas.egg-info/dependency_links.txt
dupandas.egg-info/top_level.txt