Metadata-Version: 1.1
Name: dupandas
Version: 0.3.2
Summary: python package to deduplicate text data in pandas dataframe using flexible string matching and cleaning
Home-page: https://github.com/shivam5992/dupandas
Author: Shivam Bansal
Author-email: shivam5992@gmail.com
License: MIT
Keywords: pandas,deduplication,text cleaning,flexible matching
Platform: UNKNOWN
Classifier: P
Classifier: r
Classifier: o
Classifier: g
Classifier: r
Classifier: a
Classifier: m
Classifier: m
Classifier: i
Classifier: n
Classifier: g
Classifier:  
Classifier: L
Classifier: a
Classifier: n
Classifier: g
Classifier: u
Classifier: a
Classifier: g
Classifier: e
Classifier:  
Classifier: :
Classifier: :
Classifier:  
Classifier: P
Classifier: y
Classifier: t
Classifier: h
Classifier: o
Classifier: n
